compliance_assist
