Metadata-Version: 1.2
Name: compliance-assist
Version: 0.1.dev2
Summary: Webdriver for Compliance Assist scripting, built on Selenium
Home-page: https://github.com/mattl3w1s/sjc-compliance-assist
Author: Matt Lewis
Author-email: matt@csiga.org
License: MIT
Platform: UNKNOWN
Requires-Python: >=3
